Metadata-Version: 1.1
Name: django-matome
Version: 0.0.1
Summary: Django commands for reporting code statistics (Classes, KLOCs, etc) from your django project.Reporting Ruby on Rails' rake stats like stats.
Home-page: https://github.com/keitaoouchi/django-matome
Author: Keita Oouchi
Author-email: keita.oouchi@gmail.com
License: BSD License
Platform: UNKNOWN
Classifier: Development Status :: 4 - Beta
Classifier: Intended Audience :: Developers
Classifier: License :: OSI Approved :: BSD License
Classifier: Operating System :: OS Independent
Classifier: Programming Language :: Python
Classifier: Programming Language :: Python :: 2
Classifier: Programming Language :: Python :: 3
Classifier: Programming Language :: Python :: 2.7
Classifier: Programming Language :: Python :: 3.2
Classifier: Programming Language :: Python :: 3.3
Classifier: Programming Language :: Python :: 3.4
Classifier: Topic :: Software Development :: Libraries :: Python Modules
Classifier: Framework :: Django
